spacy_legacy/__init__.py
spacy_legacy/loggers.py
spacy_legacy/architectures/__init__.py
spacy_legacy/architectures/parser.py
spacy_legacy/architectures/textcat.py
spacy_legacy/architectures/tok2vec.py
spacy_legacy/layers/__init__.py
spacy_legacy/layers/staticvectors_v1.py
spacy_legacy/tests/__init__.py
spacy_legacy/tests/test_legacy.py
spacy_legacy-3.0.7.dist-info/LICENSE
spacy_legacy-3.0.7.dist-info/METADATA
spacy_legacy-3.0.7.dist-info/WHEEL
spacy_legacy-3.0.7.dist-info/entry_points.txt
spacy_legacy-3.0.7.dist-info/top_level.txt
spacy_legacy-3.0.7.dist-info/zip-safe
spacy_legacy-3.0.7.dist-info/RECORD
